<?xml version="1.0" encoding="ISO-8859-1"?><pnml>
    <net id="Net-One" type="P/T net">
        <token id="Default" enabled="true" red="0" green="0" blue="0"/>
        <place id="P0">
            <graphics>
                <position x="257.1428571428571" y="104.28571428571428"/>
            </graphics>
            <name>
                <value>P0</value>
                <graphics>
                    <offset x="0.0" y="0.0"/>
                </graphics>
            </name>
            <initialMarking>
                <value>Default,1</value>
                <graphics>
                    <offset x="0.0" y="0.0"/>
                </graphics>
            </initialMarking>
            <capacity>
                <value>0</value>
            </capacity>
        </place>
        <place id="P1">
            <graphics>
                <position x="257.1428571428571" y="224.28571428571428"/>
            </graphics>
            <name>
                <value>P1</value>
                <graphics>
                    <offset x="0.0" y="0.0"/>
                </graphics>
            </name>
            <initialMarking>
                <value>Default,0</value>
                <graphics>
                    <offset x="0.0" y="0.0"/>
                </graphics>
            </initialMarking>
            <capacity>
                <value>0</value>
            </capacity>
        </place>
        <place id="P2">
            <graphics>
                <position x="257.1428571428571" y="344.2857142857143"/>
            </graphics>
            <name>
                <value>P2</value>
                <graphics>
                    <offset x="0.0" y="0.0"/>
                </graphics>
            </name>
            <initialMarking>
                <value>Default,0</value>
                <graphics>
                    <offset x="0.0" y="0.0"/>
                </graphics>
            </initialMarking>
            <capacity>
                <value>0</value>
            </capacity>
        </place>
        <place id="P3">
            <graphics>
                <position x="527.1428571428572" y="104.28571428571428"/>
            </graphics>
            <name>
                <value>P3</value>
                <graphics>
                    <offset x="0.0" y="0.0"/>
                </graphics>
            </name>
            <initialMarking>
                <value>Default,1</value>
                <graphics>
                    <offset x="0.0" y="0.0"/>
                </graphics>
            </initialMarking>
            <capacity>
                <value>0</value>
            </capacity>
        </place>
        <place id="P4">
            <graphics>
                <position x="527.1428571428572" y="224.28571428571428"/>
            </graphics>
            <name>
                <value>P4</value>
                <graphics>
                    <offset x="0.0" y="0.0"/>
                </graphics>
            </name>
            <initialMarking>
                <value>Default,0</value>
                <graphics>
                    <offset x="0.0" y="0.0"/>
                </graphics>
            </initialMarking>
            <capacity>
                <value>0</value>
            </capacity>
        </place>
        <place id="P5">
            <graphics>
                <position x="527.1428571428572" y="344.2857142857143"/>
            </graphics>
            <name>
                <value>P5</value>
                <graphics>
                    <offset x="0.0" y="0.0"/>
                </graphics>
            </name>
            <initialMarking>
                <value>Default,0</value>
                <graphics>
                    <offset x="0.0" y="0.0"/>
                </graphics>
            </initialMarking>
            <capacity>
                <value>0</value>
            </capacity>
        </place>
        <place id="P6">
            <graphics>
                <position x="392.142857142857" y="194.28571428571428"/>
            </graphics>
            <name>
                <value>P6</value>
                <graphics>
                    <offset x="0.0" y="0.0"/>
                </graphics>
            </name>
            <initialMarking>
                <value>Default,0</value>
                <graphics>
                    <offset x="0.0" y="0.0"/>
                </graphics>
            </initialMarking>
            <capacity>
                <value>0</value>
            </capacity>
        </place>
        <place id="P7">
            <graphics>
                <position x="392.142857142857" y="284.2857142857142"/>
            </graphics>
            <name>
                <value>P7</value>
                <graphics>
                    <offset x="0.0" y="0.0"/>
                </graphics>
            </name>
            <initialMarking>
                <value>Default,3</value>
                <graphics>
                    <offset x="0.0" y="0.0"/>
                </graphics>
            </initialMarking>
            <capacity>
                <value>0</value>
            </capacity>
        </place>
        <transition id="T0">
            <graphics>
                <position x="257.1428571428571" y="164.28571428571428"/>
            </graphics>
            <name>
                <value>T0</value>
                <graphics>
                    <offset x="0.0" y="0.0"/>
                </graphics>
            </name>
            <orientation>
                <value>90</value>
            </orientation>
            <rate>
                <value>1.0</value>
            </rate>
            <timed>
                <value>false</value>
            </timed>
            <infiniteServer>
                <value>false</value>
            </infiniteServer>
            <priority>
                <value>1</value>
            </priority>
        </transition>
        <transition id="T1">
            <graphics>
                <position x="527.1428571428572" y="164.28571428571428"/>
            </graphics>
            <name>
                <value>T1</value>
                <graphics>
                    <offset x="0.0" y="0.0"/>
                </graphics>
            </name>
            <orientation>
                <value>90</value>
            </orientation>
            <rate>
                <value>1.0</value>
            </rate>
            <timed>
                <value>false</value>
            </timed>
            <infiniteServer>
                <value>false</value>
            </infiniteServer>
            <priority>
                <value>1</value>
            </priority>
        </transition>
        <transition id="T2">
            <graphics>
                <position x="527.1428571428572" y="299.2857142857142"/>
            </graphics>
            <name>
                <value>T2</value>
                <graphics>
                    <offset x="0.0" y="0.0"/>
                </graphics>
            </name>
            <orientation>
                <value>90</value>
            </orientation>
            <rate>
                <value>1.0</value>
            </rate>
            <timed>
                <value>false</value>
            </timed>
            <infiniteServer>
                <value>false</value>
            </infiniteServer>
            <priority>
                <value>1</value>
            </priority>
        </transition>
        <transition id="T3">
            <graphics>
                <position x="257.1428571428571" y="299.2857142857142"/>
            </graphics>
            <name>
                <value>T3</value>
                <graphics>
                    <offset x="0.0" y="0.0"/>
                </graphics>
            </name>
            <orientation>
                <value>90</value>
            </orientation>
            <rate>
                <value>1.0</value>
            </rate>
            <timed>
                <value>false</value>
            </timed>
            <infiniteServer>
                <value>false</value>
            </infiniteServer>
            <priority>
                <value>1</value>
            </priority>
        </transition>
        <transition id="T4">
            <graphics>
                <position x="167.1428571428571" y="224.28571428571428"/>
            </graphics>
            <name>
                <value>T4</value>
                <graphics>
                    <offset x="0.0" y="0.0"/>
                </graphics>
            </name>
            <orientation>
                <value>90</value>
            </orientation>
            <rate>
                <value>1.0</value>
            </rate>
            <timed>
                <value>true</value>
            </timed>
            <infiniteServer>
                <value>false</value>
            </infiniteServer>
            <priority>
                <value>1</value>
            </priority>
        </transition>
        <transition id="T5">
            <graphics>
                <position x="632.1428571428572" y="224.28571428571428"/>
            </graphics>
            <name>
                <value>T5</value>
                <graphics>
                    <offset x="0.0" y="0.0"/>
                </graphics>
            </name>
            <orientation>
                <value>90</value>
            </orientation>
            <rate>
                <value>1.0</value>
            </rate>
            <timed>
                <value>true</value>
            </timed>
            <infiniteServer>
                <value>false</value>
            </infiniteServer>
            <priority>
                <value>1</value>
            </priority>
        </transition>
        <arc id="P0 to T0" source="P0" target="T0">
            <graphics/>
            <inscription>
                <value>Default,1</value>
                <graphics/>
            </inscription>
            <tagged>
                <value>false</value>
            </tagged>
            <arcpath id="000" x="269" y="131" curvePoint="false"/>
            <arcpath id="001" x="269" y="171" curvePoint="false"/>
            <type value="normal"/>
        </arc>
        <arc id="P1 to T3" source="P1" target="T3">
            <graphics/>
            <inscription>
                <value>Default,1</value>
                <graphics/>
            </inscription>
            <tagged>
                <value>false</value>
            </tagged>
            <arcpath id="000" x="269" y="251" curvePoint="false"/>
            <arcpath id="001" x="269" y="306" curvePoint="false"/>
            <type value="normal"/>
        </arc>
        <arc id="P2 to T4" source="P2" target="T4">
            <graphics/>
            <inscription>
                <value>Default,1</value>
                <graphics/>
            </inscription>
            <tagged>
                <value>false</value>
            </tagged>
            <arcpath id="000" x="260" y="345" curvePoint="false"/>
            <arcpath id="001" x="179" y="241" curvePoint="false"/>
            <type value="normal"/>
        </arc>
        <arc id="P3 to T1" source="P3" target="T1">
            <graphics/>
            <inscription>
                <value>Default,1</value>
                <graphics/>
            </inscription>
            <tagged>
                <value>false</value>
            </tagged>
            <arcpath id="000" x="539" y="131" curvePoint="false"/>
            <arcpath id="001" x="539" y="171" curvePoint="false"/>
            <type value="normal"/>
        </arc>
        <arc id="P4 to T2" source="P4" target="T2">
            <graphics/>
            <inscription>
                <value>Default,1</value>
                <graphics/>
            </inscription>
            <tagged>
                <value>false</value>
            </tagged>
            <arcpath id="000" x="539" y="251" curvePoint="false"/>
            <arcpath id="001" x="539" y="306" curvePoint="false"/>
            <type value="normal"/>
        </arc>
        <arc id="P5 to T5" source="P5" target="T5">
            <graphics/>
            <inscription>
                <value>Default,1</value>
                <graphics/>
            </inscription>
            <tagged>
                <value>false</value>
            </tagged>
            <arcpath id="000" x="550" y="345" curvePoint="false"/>
            <arcpath id="001" x="644" y="241" curvePoint="false"/>
            <type value="normal"/>
        </arc>
        <arc id="P6 to T1" source="P6" target="T1">
            <graphics/>
            <inscription>
                <value>Default,1</value>
                <graphics/>
            </inscription>
            <tagged>
                <value>false</value>
            </tagged>
            <arcpath id="000" x="419" y="203" curvePoint="false"/>
            <arcpath id="001" x="524" y="177" curvePoint="false"/>
            <type value="normal"/>
        </arc>
        <arc id="P7 to T0" source="P7" target="T0">
            <graphics/>
            <inscription>
                <value>Default,1</value>
                <graphics/>
            </inscription>
            <tagged>
                <value>false</value>
            </tagged>
            <arcpath id="000" x="393" y="287" curvePoint="false"/>
            <arcpath id="001" x="274" y="182" curvePoint="false"/>
            <type value="normal"/>
        </arc>
        <arc id="T0 to P1" source="T0" target="P1">
            <graphics/>
            <inscription>
                <value>Default,1</value>
                <graphics/>
            </inscription>
            <tagged>
                <value>false</value>
            </tagged>
            <arcpath id="000" x="264" y="181" curvePoint="false"/>
            <arcpath id="001" x="268" y="221" curvePoint="false"/>
            <type value="normal"/>
        </arc>
        <arc id="T0 to P6" source="T0" target="P6">
            <graphics/>
            <inscription>
                <value>Default,1</value>
                <graphics/>
            </inscription>
            <tagged>
                <value>false</value>
            </tagged>
            <arcpath id="000" x="284" y="177" curvePoint="false"/>
            <arcpath id="001" x="390" y="203" curvePoint="false"/>
            <type value="normal"/>
        </arc>
        <arc id="T1 to P4" source="T1" target="P4">
            <graphics/>
            <inscription>
                <value>Default,1</value>
                <graphics/>
            </inscription>
            <tagged>
                <value>false</value>
            </tagged>
            <arcpath id="000" x="544" y="182" curvePoint="false"/>
            <arcpath id="001" x="540" y="221" curvePoint="false"/>
            <type value="normal"/>
        </arc>
        <arc id="T1 to P7" source="T1" target="P7">
            <graphics/>
            <inscription>
                <value>Default,1</value>
                <graphics/>
            </inscription>
            <tagged>
                <value>false</value>
            </tagged>
            <arcpath id="000" x="534" y="181" curvePoint="false"/>
            <arcpath id="001" x="416" y="287" curvePoint="false"/>
            <type value="normal"/>
        </arc>
        <arc id="T2 to P5" source="T2" target="P5">
            <graphics/>
            <inscription>
                <value>Default,1</value>
                <graphics/>
            </inscription>
            <tagged>
                <value>false</value>
            </tagged>
            <arcpath id="000" x="539" y="316" curvePoint="false"/>
            <arcpath id="001" x="539" y="341" curvePoint="false"/>
            <type value="normal"/>
        </arc>
        <arc id="T3 to P2" source="T3" target="P2">
            <graphics/>
            <inscription>
                <value>Default,1</value>
                <graphics/>
            </inscription>
            <tagged>
                <value>false</value>
            </tagged>
            <arcpath id="000" x="269" y="316" curvePoint="false"/>
            <arcpath id="001" x="269" y="341" curvePoint="false"/>
            <type value="normal"/>
        </arc>
        <arc id="T4 to P0" source="T4" target="P0">
            <graphics/>
            <inscription>
                <value>Default,1</value>
                <graphics/>
            </inscription>
            <tagged>
                <value>false</value>
            </tagged>
            <arcpath id="000" x="179" y="231" curvePoint="false"/>
            <arcpath id="001" x="260" y="128" curvePoint="false"/>
            <type value="normal"/>
        </arc>
        <arc id="T5 to P3" source="T5" target="P3">
            <graphics/>
            <inscription>
                <value>Default,1</value>
                <graphics/>
            </inscription>
            <tagged>
                <value>false</value>
            </tagged>
            <arcpath id="000" x="643" y="231" curvePoint="false"/>
            <arcpath id="001" x="550" y="128" curvePoint="false"/>
            <type value="normal"/>
        </arc>
    </net>
</pnml>
